convertunit/__init__.py
convertunit/conv.py
convertunit-1.0.1.dist-info/LICENSE
convertunit-1.0.1.dist-info/METADATA
convertunit-1.0.1.dist-info/WHEEL
convertunit-1.0.1.dist-info/top_level.txt
convertunit-1.0.1.dist-info/RECORD
