Metadata-Version: 2.1
Name: convertunit
Version: 1.0.1
Summary: For Converting various units.
Home-page: https://github.com/Asylum0741/UnitConverter
Author: Prabhat Mukhiya
Author-email: prabhatmukhiya3@gmail.com
Classifier: Programming Language :: Python :: 3
Classifier: License :: OSI Approved :: MIT License
Classifier: Operating System :: OS Independent
Requires-Python: >=3.6
License-File: LICENSE
